bcipy/__init__.py
bcipy/config.py
bcipy/exceptions.py
bcipy/main.py
bcipy/preferences.py
bcipy/acquisition/__init__.py
bcipy/acquisition/devices.py
bcipy/acquisition/exceptions.py
bcipy/acquisition/marker_writer.py
bcipy/acquisition/multimodal.py
bcipy/acquisition/record.py
bcipy/acquisition/util.py
bcipy/acquisition/datastream/__init__.py
bcipy/acquisition/datastream/generator.py
bcipy/acquisition/datastream/lsl_server.py
bcipy/acquisition/datastream/producer.py
bcipy/acquisition/datastream/mock/__init__.py
bcipy/acquisition/datastream/mock/eye_tracker_server.py
bcipy/acquisition/datastream/mock/switch.py
bcipy/acquisition/demo/demo_eeg_with_switch.py
bcipy/acquisition/demo/demo_eye_tracker_client_and_server.py
bcipy/acquisition/demo/demo_lsl_acq_client.py
bcipy/acquisition/demo/demo_lsl_recorder.py
bcipy/acquisition/demo/demo_lsl_server.py
bcipy/acquisition/demo/demo_switch.py
bcipy/acquisition/protocols/__init__.py
bcipy/acquisition/protocols/lsl/__init__.py
bcipy/acquisition/protocols/lsl/connect.py
bcipy/acquisition/protocols/lsl/lsl_client.py
bcipy/acquisition/protocols/lsl/lsl_connector.py
bcipy/acquisition/protocols/lsl/lsl_recorder.py
bcipy/acquisition/tests/test_client_manager.py
bcipy/acquisition/tests/test_content_type.py
bcipy/acquisition/tests/test_devices.py
bcipy/acquisition/tests/datastream/test_generator.py
bcipy/acquisition/tests/datastream/test_producer.py
bcipy/acquisition/tests/protocols/lsl/test_lsl_client.py
bcipy/acquisition/tests/protocols/lsl/test_lsl_recorder.py
bcipy/core/__init__.py
bcipy/core/list.py
bcipy/core/parameters.py
bcipy/core/raw_data.py
bcipy/core/report.py
bcipy/core/session.py
bcipy/core/stimuli.py
bcipy/core/symbols.py
bcipy/core/triggers.py
bcipy/core/demo/demo_report.py
bcipy/core/demo/demo_session_tools.py
bcipy/core/demo/demo_stimuli_generation.py
bcipy/core/tests/test_list.py
bcipy/core/tests/test_parameters.py
bcipy/core/tests/test_raw_data.py
bcipy/core/tests/test_report.py
bcipy/core/tests/test_session.py
bcipy-2.0.1.dist-info/licenses/LICENSE.md
bcipy-2.0.1.dist-info/METADATA
bcipy-2.0.1.dist-info/WHEEL
bcipy-2.0.1.dist-info/entry_points.txt
bcipy-2.0.1.dist-info/top_level.txt
bcipy-2.0.1.dist-info/zip-safe
bcipy-2.0.1.dist-info/RECORD
