Metadata-Version: 2.4
Name: bcipy
Version: 2.0.1
Summary: Python Software for Brain-Computer Interface Development.
Author-email: CAMBI <cambi_support@googlegroups.com>
License: Copyright 2025 (CAMBI)("Licensor")
Project-URL: Homepage, https://www.cambi.tech/
Project-URL: Documentation, https://bcipy.github.io/
Project-URL: Source, https://github.com/CAMBI-tech/BciPy
Platform: Linux
Platform: Windows
Platform: Mac OS-X
Classifier: License :: Other/Proprietary License
Classifier: Topic :: Scientific/Engineering :: Human Machine Interfaces
Classifier: Intended Audience :: Science/Research
Classifier: Intended Audience :: End Users/Desktop
Classifier: Intended Audience :: Developers
Classifier: Programming Language :: Python
Classifier: Programming Language :: Python :: 3.9
Classifier: Programming Language :: Python :: 3.10
Requires-Python: <3.11,>3.8
License-File: LICENSE.md
Requires-Dist: textslinger~=0.1.1
Requires-Dist: attrdict3==2.0.2
Requires-Dist: EDFlib-Python==1.0.8
Requires-Dist: torch==2.2.0
Requires-Dist: construct==2.8.14
Requires-Dist: mne==1.6.1
Requires-Dist: mne-bids==0.14.0
Requires-Dist: pyobjc==7.3; platform_system == "Darwin"
Requires-Dist: pybv==0.7.5
Requires-Dist: pyo==1.0.5
Requires-Dist: pyglet<=1.5.27,>=1.4
Requires-Dist: PsychoPy==2025.1.1
Requires-Dist: openpyxl==3.1.2
Requires-Dist: numpy==1.24.4
Requires-Dist: sounddevice==0.4.4
Requires-Dist: SoundFile==0.12.1
Requires-Dist: scipy==1.10.1
Requires-Dist: scikit-learn==1.2.2
Requires-Dist: seaborn==0.13.2
Requires-Dist: matplotlib==3.7.5
Requires-Dist: pylsl==1.16.2
Requires-Dist: pandas==2.0.3
Requires-Dist: psutil==5.7.2
Requires-Dist: Pillow==10.2.0
Requires-Dist: py-cpuinfo==9.0.0
Requires-Dist: pyopengl==3.1.7
Requires-Dist: PyQt6==6.7.1
Requires-Dist: PyQt6-sip==13.8
Requires-Dist: pywavelets==1.4.1
Requires-Dist: tqdm==4.62.2
Requires-Dist: rich==13.9.4
Requires-Dist: reportlab==4.2.0
Requires-Dist: tables==3.9.1
Requires-Dist: pyWinhook==1.6.2; python_version == "3.9" and platform_system == "Windows"
Requires-Dist: WxPython==4.2.1; platform_system != "Linux"
Provides-Extra: dev
Requires-Dist: autopep8==1.5.7; extra == "dev"
Requires-Dist: coverage>=7.0; extra == "dev"
Requires-Dist: flake8==5.0.4; extra == "dev"
Requires-Dist: Flake8-pyproject==1.2.3; extra == "dev"
Requires-Dist: flake8-docstrings==1.7.0; extra == "dev"
Requires-Dist: mypy==1.13; extra == "dev"
Requires-Dist: lxml; extra == "dev"
Requires-Dist: mock; extra == "dev"
Requires-Dist: mockito; extra == "dev"
Requires-Dist: pylint; extra == "dev"
Requires-Dist: pytest; extra == "dev"
Requires-Dist: pytest-mpl; extra == "dev"
Provides-Extra: release
Requires-Dist: twine==3.2.0; extra == "release"
Requires-Dist: build==1.2.2.post1; extra == "release"
Requires-Dist: pyinstaller==6.13.0; extra == "release"
Requires-Dist: wheel==0.43.0; extra == "release"
Dynamic: license-file
